dowg/__init__.py
dowg/dowg.py
dowgopt-0.13.dist-info/METADATA
dowgopt-0.13.dist-info/WHEEL
dowgopt-0.13.dist-info/top_level.txt
dowgopt-0.13.dist-info/RECORD
