Metadata-Version: 2.1
Name: dowgopt
Version: 0.13
Summary: DoWG parameter-free optimizer for PyTorch
Home-page: https://github.com/rka97/dowg
Author: Ahmed Khaled
Author-email: akregeb@gmail.com
Classifier: Development Status :: 3 - Alpha
Classifier: Intended Audience :: Developers
Classifier: License :: OSI Approved :: MIT License
Classifier: Programming Language :: Python :: 3
Classifier: Programming Language :: Python :: 3.6
Classifier: Programming Language :: Python :: 3.7
Classifier: Programming Language :: Python :: 3.8
Classifier: Programming Language :: Python :: 3.9
Requires-Dist: torch
